py_spoo_url/__init__.py
py_spoo_url/shortener.py
py_spoo_url/statistics.py
py_spoo_url-0.1.dist-info/LICENSE
py_spoo_url-0.1.dist-info/METADATA
py_spoo_url-0.1.dist-info/WHEEL
py_spoo_url-0.1.dist-info/top_level.txt
py_spoo_url-0.1.dist-info/RECORD
