Metadata-Version: 2.1
Name: py_spoo_url
Version: 0.1
Summary: Simple URL shortening with advanced analytics, emoji aliases, and more using spoo.me.
Home-page: https://github.com/spoo-me/py_spoo_url
Author: https://github.com/spoo-me
Author-email: support@spoo.me
License: MIT
Project-URL: spoo.me Service, https://spoo.me
Keywords: URL shortening,spoo.me,URL analytics,emoji aliases,Python API,custom aliasing,password protection,click tracking,graph creation,country heatmaps,URL management,Python package
Classifier: Development Status :: 5 - Production/Stable
Classifier: Intended Audience :: Developers
Classifier: Intended Audience :: Customer Service
Classifier: License :: OSI Approved :: MIT License
Classifier: Natural Language :: English
Classifier: Programming Language :: Python :: 3
Classifier: Programming Language :: Python :: 3.6
Classifier: Programming Language :: Python :: 3.7
Classifier: Programming Language :: Python :: 3.8
Classifier: Programming Language :: Python :: 3.9
Classifier: Programming Language :: Python :: 3.10
Classifier: Programming Language :: Python :: 3.11
Classifier: Typing :: Typed
License-File: LICENSE
Requires-Dist: matplotlib
Requires-Dist: requests
Requires-Dist: json
Requires-Dist: datetime
Requires-Dist: geopandas
Requires-Dist: mpl-toolkits
Requires-Dist: pandas
Requires-Dist: openpyxl
